{"items":[{"custitem_ns_pr_item_attributes":"&nbsp;","ispurchasable":true,"custitem_ns_pr_attributes_rating":"","stockdescription":"","storedetaileddescription":"<span style=\"color: rgb(76, 76, 76); font-family: Lato, sans-serif; font-size: 14px; orphans: 3; widows: 3; background-color: rgb(255, 255, 255);\">The&nbsp;Performax Handle&nbsp;is a heavy duty squeegee handle that is designed to easily utilize thicker squeegee blades such as&nbsp;Blue Max, Clear Max&nbsp;and&nbsp;Orange Fusion. An extension is also easily fitted to the threaded handle.</span>","itemimages_detail":{"urls":[{"altimagetext":"","url":"https://www.xpel.com/product-images/A1400P_00.jpg"}]},"custitem_sca_item_document":"","onlinecustomerprice_detail":{"onlinecustomerprice_formatted":"USD $‎21.39","onlinecustomerprice":21.39},"custitem_ns_pr_rating_by_rate":"","pricelevel5_formatted":"USD $‎21.39","internalid":672255,"itemoptions_detail":{},"outofstockmessage":"","relateditemsdescription":"","storedescription":"The Performax Handle is a heavy duty squeegee handle that is designed to easily utilize thicker squeegee blades such as Blue Max, Clear Max and Orange Fusion. The end of the handle is threaded so that extensions can be screwed in for safety film installation requiring two hands. Made In The USA","isinstock":true,"commercecategory":{"primarypath":[{"urls":["/shop/additional-products/installation-tools"],"url_fragment_aliases":[],"name":"Installation Tools","id":19},{"urls":["/shop/additional-products"],"url_fragment_aliases":[],"name":"Additional Products","id":17},{"urls":["/shop"],"url_fragment_aliases":[],"name":"Shop","id":225}],"categories":[{"urls":["/shop/installation-tools/squeegees"],"url_fragment_aliases":[],"name":"SQUEEGEES","id":233},{"urls":["/products/additional-products/installation-tools","/shop/additional-products/installation-tools"],"url_fragment_aliases":[],"name":"Installation Tools","id":19}]},"metataghtml":"","quantityavailable_detail":{"quantityavailable":19.0,"locations":[{"internalid":27,"quantityavailable":11.0},{"internalid":106,"quantityavailable":4.0},{"internalid":82,"quantityavailable":10.0},{"internalid":107,"quantityavailable":10.0},{"internalid":25,"quantityavailable":16.0},{"internalid":8,"quantityavailable":5.0},{"internalid":37,"quantityavailable":5.0}]},"onlinecustomerprice":21.39,"itemid":"A1400P","onlinecustomerprice_formatted":"USD $‎21.39","isbackorderable":true,"showoutofstockmessage":false,"outofstockbehavior":"- Default -","custitem_sca_tool_type":"Squeegee Handles","itemtype":"InvtPart","quantityavailable":19.0,"custitem_sca_sold_by_the_foot":false,"pricelevel5":21.39,"displayname":"","storedisplayname2":"Performax Handle","pagetitle":"","urlcomponent":"performax-handle"}],"facets":[{"id":"category","values":[]},{"id":"commercecategoryname","values":[{"url":"Installation Tools"},{"url":"SQUEEGEES"}]},{"id":"custitem_sca_paint_protection_type","url":"film-type","values":[]},{"id":"custitem_sca_tool_type","url":"tool-type","values":[{"url":"Squeegee-Handles","label":"Squeegee Handles"}]}],"corrections":[],"locale":{"country":"US","language":"en","currency":"USD","region":1},"backendType":"OS","backend":"E","volatility":"short","code":200,"warnings":{}}