{"items":[{"custitem_ns_pr_item_attributes":"&nbsp;","matrixchilditems_detail":[{"isinstock":true,"itemid":"M4009-3X","ispurchasable":true,"stockdescription":"","isbackorderable":true,"onlinecustomerprice_detail":{"onlinecustomerprice_formatted":"USD $‎20.75","onlinecustomerprice":20.75},"internalid":505025,"showoutofstockmessage":false,"outofstockbehavior":"- Default -","itemtype":"Assembly","quantityavailable":20.0,"outofstockmessage":"","custitemxpel_scamatrix_cl_l":"3X LARGE"},{"isinstock":true,"itemid":"M4009-2X","ispurchasable":true,"stockdescription":"","isbackorderable":true,"onlinecustomerprice_detail":{"onlinecustomerprice_formatted":"USD $‎20.75","onlinecustomerprice":20.75},"internalid":505024,"showoutofstockmessage":false,"outofstockbehavior":"- Default -","itemtype":"Assembly","quantityavailable":59.0,"outofstockmessage":"","custitemxpel_scamatrix_cl_l":"2X Large"},{"isinstock":true,"itemid":"M4009-XL","ispurchasable":true,"stockdescription":"","isbackorderable":true,"onlinecustomerprice_detail":{"onlinecustomerprice_formatted":"USD $‎20.75","onlinecustomerprice":20.75},"internalid":505023,"showoutofstockmessage":false,"outofstockbehavior":"- Default -","itemtype":"Assembly","quantityavailable":172.0,"outofstockmessage":"","custitemxpel_scamatrix_cl_l":"X Large"},{"isinstock":true,"itemid":"M4009-L","ispurchasable":true,"stockdescription":"","isbackorderable":true,"onlinecustomerprice_detail":{"onlinecustomerprice_formatted":"USD $‎20.75","onlinecustomerprice":20.75},"internalid":505022,"showoutofstockmessage":false,"outofstockbehavior":"- Default -","itemtype":"Assembly","quantityavailable":144.0,"outofstockmessage":"","custitemxpel_scamatrix_cl_l":"Large"},{"isinstock":true,"itemid":"M4009-M","ispurchasable":true,"stockdescription":"","isbackorderable":true,"onlinecustomerprice_detail":{"onlinecustomerprice_formatted":"USD $‎20.75","onlinecustomerprice":20.75},"internalid":505021,"showoutofstockmessage":false,"outofstockbehavior":"- Default -","itemtype":"Assembly","quantityavailable":172.0,"outofstockmessage":"","custitemxpel_scamatrix_cl_l":"Medium"},{"isinstock":true,"itemid":"M4009-S","ispurchasable":true,"stockdescription":"","isbackorderable":true,"onlinecustomerprice_detail":{"onlinecustomerprice_formatted":"USD $‎20.75","onlinecustomerprice":20.75},"internalid":505020,"showoutofstockmessage":false,"outofstockbehavior":"- Default -","itemtype":"Assembly","quantityavailable":66.0,"outofstockmessage":"","custitemxpel_scamatrix_cl_l":"Small"}],"ispurchasable":true,"custitem_ns_pr_attributes_rating":"","stockdescription":"","storedetaileddescription":"<p>BELLA+CANVAS uses sustainable manufacturing processes with Blue Sign certified dyes, efficient dye houses that adhere to the state of California’s EPA regulations around waste water treatment and usage, and cutting facilities in Los Angeles that run on partial solar power with comprehensive recycling programs for paper waste and fabric scraps. Retail fit, Unisex sizing, Sideseamed, Tear away label, Pre-shrunk.&nbsp;</p>","itemimages_detail":{"urls":[{"altimagetext":"","url":"https://www.xpel.com/product-images/M4009_00.png"},{"altimagetext":"","url":"https://www.xpel.com/product-images/M4009_01.png"}]},"custitem_sca_item_document":"","onlinecustomerprice_detail":{"onlinecustomerprice_formatted":"USD $‎20.75","onlinecustomerprice":20.75},"custitem_ns_pr_rating_by_rate":"","pricelevel5_formatted":"USD $‎20.75","internalid":505019,"itemoptions_detail":{"matrixtype":"parent","fields":[{"ismandatory":true,"internalid":"custcolxpel_scamatrix_cl_l","ismatrixdimension":true,"values":[{"label":"- Select -"},{"internalid":"57","label":"Small"},{"internalid":"58","label":"Medium"},{"internalid":"59","label":"Large"},{"internalid":"60","label":"X Large"},{"internalid":"61","label":"2X Large"},{"internalid":"62","label":"3X LARGE"}],"label":"SCA Matrix CL - Length","type":"select","sourcefrom":"custitemxpel_scamatrix_cl_l"}]},"outofstockmessage":"","relateditemsdescription":"","storedescription":"<p>BELLA+CANVAS uses sustainable manufacturing processes with Blue Sign certified dyes, efficient dye houses that adhere to the state of California’s EPA regulations around waste water treatment and usage, and cutting facilities in Los Angeles that run on partial solar power with comprehensive recycling programs for paper waste and fabric scraps. Retail fit, Unisex sizing, Sideseamed, Tear away label, Pre-shrunk.&nbsp;</p>","isinstock":true,"commercecategory":{"primarypath":[],"categories":[{"urls":["/shop/lifestyle/shirts"],"url_fragment_aliases":[],"name":"SHIRTS","id":247}]},"metataghtml":"","quantityavailable_detail":{"quantityavailable":633.0,"locations":[{"internalid":22,"quantityavailable":1.0},{"internalid":27,"quantityavailable":1.0},{"internalid":106,"quantityavailable":1.0},{"internalid":82,"quantityavailable":1.0},{"internalid":107,"quantityavailable":1.0},{"internalid":25,"quantityavailable":1.0},{"internalid":8,"quantityavailable":1.0},{"internalid":37,"quantityavailable":1.0}]},"onlinecustomerprice":20.75,"itemid":"M4009","onlinecustomerprice_formatted":"USD $‎20.75","isbackorderable":true,"showoutofstockmessage":false,"outofstockbehavior":"- Default -","custitem_sca_tool_type":"Shirts","itemtype":"Assembly","quantityavailable":633.0,"custitem_sca_sold_by_the_foot":false,"pricelevel5":20.75,"displayname":"","storedisplayname2":"XPEL Unisex Grey Tri-Blend Sunset T-Shirt","pagetitle":"","urlcomponent":"XPEL-Grey-Tri-Blend-Sunset-T-Shirt"}],"facets":[{"id":"category","values":[]},{"id":"commercecategoryname","values":[{"url":"SHIRTS"}]},{"id":"custitem_sca_paint_protection_type","url":"film-type","values":[]},{"id":"custitem_sca_tool_type","url":"tool-type","values":[{"url":"Shirts","label":"Shirts"}]}],"corrections":[],"locale":{"country":"US","language":"en","currency":"USD","region":1},"backendType":"OS","backend":"E","volatility":"short","code":200,"warnings":{}}